CHANGELOG.md
LICENSE
MANIFEST.in
README.md
setup.cfg
setup.py
pip_services3_components/Component.py
pip_services3_components/__init__.py
pip_services3_components.egg-info/PKG-INFO
pip_services3_components.egg-info/SOURCES.txt
pip_services3_components.egg-info/dependency_links.txt
pip_services3_components.egg-info/requires.txt
pip_services3_components.egg-info/top_level.txt
pip_services3_components.egg-info/zip-safe
pip_services3_components/auth/CredentialParams.py
pip_services3_components/auth/CredentialResolver.py
pip_services3_components/auth/DefaultCredentialStoreFactory.py
pip_services3_components/auth/ICredentialStore.py
pip_services3_components/auth/MemoryCredentialStore.py
pip_services3_components/auth/__init__.py
pip_services3_components/build/CompositeFactory.py
pip_services3_components/build/CreateException.py
pip_services3_components/build/Factory.py
pip_services3_components/build/IFactory.py
pip_services3_components/build/__init__.py
pip_services3_components/cache/CacheEntry.py
pip_services3_components/cache/DefaultCacheFactory.py
pip_services3_components/cache/ICache.py
pip_services3_components/cache/MemoryCache.py
pip_services3_components/cache/NullCache.py
pip_services3_components/cache/__init__.py
pip_services3_components/config/ConfigReader.py
pip_services3_components/config/DefaultConfigReaderFactory.py
pip_services3_components/config/FileConfigReader.py
pip_services3_components/config/IConfigReader.py
pip_services3_components/config/JsonConfigReader.py
pip_services3_components/config/MemoryConfigReader.py
pip_services3_components/config/YamlConfigReader.py
pip_services3_components/config/__init__.py
pip_services3_components/connect/CompositeConnectionResolver.py
pip_services3_components/connect/ConnectionParams.py
pip_services3_components/connect/ConnectionResolver.py
pip_services3_components/connect/ConnectionUtils.py
pip_services3_components/connect/DefaultDiscoveryFactory.py
pip_services3_components/connect/IDiscovery.py
pip_services3_components/connect/MemoryDiscovery.py
pip_services3_components/connect/__init__.py
pip_services3_components/count/CachedCounters.py
pip_services3_components/count/CompositeCounters.py
pip_services3_components/count/Counter.py
pip_services3_components/count/CounterTiming.py
